README.rst
setup.py
sqlalchemy_vertica/__init__.py
sqlalchemy_vertica/base.py
vertica_sqlalchemy.egg-info/PKG-INFO
vertica_sqlalchemy.egg-info/SOURCES.txt
vertica_sqlalchemy.egg-info/dependency_links.txt
vertica_sqlalchemy.egg-info/entry_points.txt
vertica_sqlalchemy.egg-info/top_level.txt