Metadata-Version: 1.1
Name: vertica-sqlalchemy
Version: 0.13
Summary: Vertica dialect for sqlalchemy
Home-page: https://github.com/jamescasbon/vertica-sqlalchemy
Author: James Casbon
Author-email: casbon@gmail.com
License: MIT
Platform: UNKNOWN
Classifier: Development Status :: 3 - Alpha
Classifier: Intended Audience :: Developers
Classifier: License :: OSI Approved :: MIT License
Classifier: Operating System :: OS Independent
Classifier: Programming Language :: Python
